{"results":[{"address_components":[{"long_name":"Unnamed Road","short_name":"Unnamed Road","types":["route"]},{"long_name":"El Nido","short_name":"El Nido","types":["locality","political"]},{"long_name":"Philippines","short_name":"PH","types":["country","political"]}],"formatted_address":"Unnamed Road, El Nido, Philippines","place_id":"ChIJ5zSL530DtzMRyAtxs_Zv4EQ","geometry":{"bounds":{"northeast":{"lat":11.263459,"lng":119.5636494},"southwest":{"lat":11.2627831,"lng":119.5622055}},"location":{"lat":11.262823,"lng":119.5631962},"location_type":"GEOMETRIC_CENTER","types":null},"types":["route"]},{"address_components":[{"long_name":"Philippines","short_name":"PH","types":["country","political"]}],"formatted_address":"Philippines","place_id":"ChIJY96HXyFTQDIRV9opeu-QR3g","geometry":{"bounds":{"northeast":{"lat":19.932,"lng":127.6444784},"southwest":{"lat":4.2259,"lng":116.1474999}},"location":{"lat":12.879721,"lng":121.774017},"location_type":"APPROXIMATE","types":null},"types":["country","political"]}],"City":null,"IsValid":true}